plus/__init__.py
plus/base/__init__.py
plus/config/__init__.py
plus/config/config.py
plus/config/config_manager.py
plus/config/utils.py
plus/config/netcfgs/__init__.py
plus/config/netcfgs/basic_modules_spec.py
plus/config/netcfgs/net_spec_edict.py
plus/config/paracfgs/__init__.py
plus/config/paracfgs/class_example.py
plus/config/paracfgs/edict_example.py
plus/dataset/__init__.py
plus/dataset/batchdataset.py
plus/dataset/concatdataset.py
plus/dataset/dataset.py
plus/dataset/listdataset.py
plus/dataset/resampledataset.py
plus/dataset/shuffledataset.py
plus/dataset/splitdataset.py
plus/dataset/tensordataset.py
plus/dataset/transformdataset.py
plus/examples/__init__.py
plus/examples/demo_plotter.py
plus/logger/__init__.py
plus/logger/logger.py
plus/logger/visdomlogger.py
plus/meter/__init__.py
plus/meter/apmeter.py
plus/meter/aucmeter.py
plus/meter/averagevaluemeter.py
plus/meter/classerrormeter.py
plus/meter/confusionmeter.py
plus/meter/mapmeter.py
plus/meter/meter.py
plus/meter/movingaveragevaluemeter.py
plus/meter/msemeter.py
plus/meter/timemeter.py
plus/opt/__init__.py
plus/opt/hyper_optimizer.py
plus/plus/__init__.py
plus/plus/plotter.py
plus/plus/visual.py
plus/test/__init__.py
plus/test/test.py
plus/test/test_config.py
plus/test/test_utils.py
plus/test/test_visual.py
plus/utils/__init__.py
plus/utils/debugger.py
plus/utils/table.py
plus/utils/utils.py
plus/visual/__init__.py
plus/visual/plotter.py
plus/visual/visual.py
plus-1994.12.4.dist-info/DESCRIPTION.rst
plus-1994.12.4.dist-info/METADATA
plus-1994.12.4.dist-info/RECORD
plus-1994.12.4.dist-info/WHEEL
plus-1994.12.4.dist-info/metadata.json
plus-1994.12.4.dist-info/top_level.txt
venus/__init__.py
venus/base/__init__.py
venus/config/__init__.py
venus/config/config.py
venus/config/config_manager.py
venus/config/utils.py
venus/config/netcfgs/__init__.py
venus/config/netcfgs/basic_modules_spec.py
venus/config/netcfgs/net_spec_edict.py
venus/config/paracfgs/__init__.py
venus/config/paracfgs/class_example.py
venus/config/paracfgs/edict_example.py
venus/dataset/__init__.py
venus/dataset/batchdataset.py
venus/dataset/concatdataset.py
venus/dataset/dataset.py
