Metadata-Version: 1.2
Name: plus
Version: 1994.12.4
Summary: A tool for helping you config, visualize, log and debug deep learning.
Home-page: https://github.com/SHTUPLUS/Venus
Author: Rhysiyan
Author-email: yanshp@shanghaitech.com
License: MIT
Platform: UNKNOWN
Classifier: License :: OSI Approved :: MIT License
Classifier: Programming Language :: Python
Classifier: Programming Language :: Python :: 3
Classifier: Programming Language :: Python :: 3.6
Classifier: Programming Language :: Python :: Implementation :: CPython
Classifier: Programming Language :: Python :: Implementation :: PyPy
Requires-Python: >=2.7.0
